polywrap_ethereum_wallet/__init__.py
polywrap_ethereum_wallet/connection.py
polywrap_ethereum_wallet/connections.py
polywrap_ethereum_wallet/networks.py
polywrap_ethereum_wallet/py.typed
polywrap_ethereum_wallet/wrap/__init__.py
polywrap_ethereum_wallet/wrap/module.py
polywrap_ethereum_wallet/wrap/types.py
polywrap_ethereum_wallet/wrap/wrap_info.py
polywrap_ethereum_wallet-0.1.2.dist-info/METADATA
polywrap_ethereum_wallet-0.1.2.dist-info/WHEEL
polywrap_ethereum_wallet-0.1.2.dist-info/RECORD
